desmos2python/__init__.py
desmos2python/_logger.py
desmos2python/api.py
desmos2python/browser.py
desmos2python/consts.py
desmos2python/latex.py
desmos2python/pdoc.py
desmos2python/render.py
desmos2python/svg.py
desmos2python/utils.py
desmos2python/_setuptools_ext/__init__.py
desmos2python/_setuptools_ext/_setuptools_ext.py
desmos2python/resources/__init__.py
desmos2python/resources/greek_alphabet.json
desmos2python/resources/greek_chars.py
desmos2python/resources/javascript/__init__.py
desmos2python/resources/javascript/get_latex_desmos.js
desmos2python/resources/javascript/get_svg.js
desmos2python/resources/javascript/take_svg_screenshot.js
desmos2python/resources/latex_json/__init__.py
desmos2python/resources/latex_json/ex.json
desmos2python/resources/screenshots/ex.svg
desmos2python/resources/templates/__init__.py
desmos2python/resources/templates/desmos_mock_graph.html.jinja2
desmos2python/resources/templates/desmos_model_ns.jinja2
desmos2python-0.3.4.dist-info/AUTHORS.rst
desmos2python-0.3.4.dist-info/LICENSE
desmos2python-0.3.4.dist-info/METADATA
desmos2python-0.3.4.dist-info/WHEEL
desmos2python-0.3.4.dist-info/top_level.txt
desmos2python-0.3.4.dist-info/RECORD
