Metadata-Version: 2.1
Name: desmos2python
Version: 0.3.4
Summary: seamless conversion between Desmos LaTeX equations and executable Python code.
Home-page: https://github.com/rocapp/desmos2python
Author: Robert Ahlroth Capps
Author-email: rocapp@gmail.com
License: MIT License
Project-URL: Homepage, https://github.com/rocapp/desmos2python
Project-URL: Issue Tracker, https://github.com/rocapp/desmos2python/issues
Project-URL: Source Code, https://github.com/rocapp/desmos2python
Keywords: desmos,graphing calculator,conversion,convert to python,mathematical modeling
Platform: Windows
Platform: macOS
Platform: Linux
Classifier: License :: OSI Approved :: MIT License
Classifier: Operating System :: OS Independent
Classifier: Programming Language :: Python
Classifier: Programming Language :: Python :: 3 :: Only
Classifier: Programming Language :: Python :: 3.10
Classifier: Programming Language :: Python :: Implementation :: CPython
Requires-Python: >=3.10
License-File: LICENSE
License-File: AUTHORS.rst
Requires-Dist: setuptools (>=40.6.0)
Requires-Dist: setuptools-scm
Requires-Dist: wheel
Requires-Dist: flake8
Requires-Dist: mypy
Requires-Dist: autopep8
Requires-Dist: pypandoc
Requires-Dist: ipython (>=8.11.0)
Requires-Dist: twine
Requires-Dist: build[virtualenv] (>=0.3.1)
Requires-Dist: numpy
Requires-Dist: matplotlib
Requires-Dist: jinja2 (==3.1.2)
Requires-Dist: jinja2-cli
Requires-Dist: sympy (==1.11.1)
Requires-Dist: antlr4-python3-runtime (==4.10)
Requires-Dist: selenium
Requires-Dist: pandas (>=1.5.3)
Requires-Dist: svg.path
